django_paginated_urls-0.1.6.dist-info/DESCRIPTION.rst
django_paginated_urls-0.1.6.dist-info/METADATA
django_paginated_urls-0.1.6.dist-info/metadata.json
django_paginated_urls-0.1.6.dist-info/RECORD
django_paginated_urls-0.1.6.dist-info/top_level.txt
django_paginated_urls-0.1.6.dist-info/WHEEL
paginated_urls/__init__.py
paginated_urls/middleware.py
paginated_urls/models.py
paginated_urls/urlresolvers.py
paginated_urls/utils.py
paginated_urls/views.py
paginated_urls/static/css/paginated_urls.css
paginated_urls/static/js/paginated_urls.js
paginated_urls/templates/paginated_urls/base.html
paginated_urls/templatetags/__init__.py
paginated_urls/templatetags/paginated_urls.py
