Metadata-Version: 2.0
Name: django-paginated-urls
Version: 0.1.6
Summary: Helpers for returning users to the correct page of a view using pagination.
Home-page: https://github.com/liquid-state/django-paginated-urls
Author: Cyril Doussin
Author-email: cyril@liquid-state.com
License: BSD
Keywords: django-paginated-urls
Platform: UNKNOWN
Classifier: Development Status :: 3 - Alpha
Classifier: Framework :: Django
Classifier: Intended Audience :: Developers
Classifier: License :: OSI Approved :: BSD License
Classifier: Natural Language :: English
Classifier: Programming Language :: Python :: 3
Classifier: Programming Language :: Python :: 3.3
Classifier: Programming Language :: Python :: 3.4
